__init__.py
conf/__init__.py
scripts/__init__.py
scripts/ingest_data.py
scripts/load_constants.py
scripts/logger.py
scripts/main.py
scripts/score.py
scripts/train.py
housing_price_prediction_nitish-0.5.dist-info/METADATA
housing_price_prediction_nitish-0.5.dist-info/WHEEL
housing_price_prediction_nitish-0.5.dist-info/top_level.txt
housing_price_prediction_nitish-0.5.dist-info/RECORD
