Metadata-Version: 2.1
Name: housing-price-prediction-nitish
Version: 0.5
Summary: This package contains code to build multiple models to predict the house price
Author-email: nitishkumarnaramoni <nitishkumar.nara@tigeranalytics.com>
Project-URL: Homepage, https://github.com/Nitish-nara/mle-training
Project-URL: Bug Tracker, https://github.com/Nitish-nara/mle-training/issues
Classifier: Programming Language :: Python :: 3
Classifier: License :: OSI Approved :: MIT License
Classifier: Operating System :: OS Independent
Requires-Python: >=3.7
